{
  "relationships": [
    {
      "relationshipId": 1,
      "relationshipName": "conversation",
      "otherEntityName": "conversation",
      "relationshipType": "many-to-one",
      "otherEntityField": "id"
    },
    {
      "relationshipId": 2,
      "relationshipName": "user",
      "otherEntityName": "user",
      "relationshipType": "many-to-one",
      "otherEntityField": "email"
    }
  ],
  "fields": [
    {
      "fieldId": 1,
      "fieldName": "text",
      "fieldType": "String"
    },
    {
      "fieldId": 2,
      "fieldName": "time",
      "fieldType": "LocalDate"
    }
  ],
  "changelogDate": "20160329150242",
  "dto": "no",
  "pagination": "pagination",
  "service": "no"
}